digital_clock.v
module digital_clock(
    seconds_out,
    minutes_out,
    hours_out,
    am_pm_out,
    stopwatch_hours_out,
    stopwatch_minutes_out,
    stopwatch_seconds_out,
    alarm_ring_out, 
    Clk_1sec, 
    reset_in, 
    set_time_in, 
    set_hour_in, 
    set_minute_in, 
    set_ampm_in,
    alarm_hour_in,
    alarm_minute_in,
    alarm_ampm_in, 
    stopwatch_on_in,
    stopwatch_reset_in
); 

// Outputs
output [5:0] seconds_out;
output [5:0] minutes_out;
output [3:0] hours_out;
output am_pm_out;
output [3:0] stopwatch_hours_out;
output [5:0] stopwatch_minutes_out;
output [5:0] stopwatch_seconds_out;
output alarm_ring_out; 

// Inputs
input Clk_1sec; // Clock with 1 Hz frequency
input reset_in; // Active high reset
input set_time_in; // Input 1 to select set time option
input [3:0] set_hour_in; // Input hour
input [5:0] set_minute_in; // Input minute
input set_ampm_in; // 0 for am and 1 for pm
input [3:0] alarm_hour_in;
input [5:0] alarm_minute_in;
input alarm_ampm_in; // 0 for am and 1 for pm
input stopwatch_on_in;
input stopwatch_reset_in;

// Internal variables.
reg [5:0] seconds_out;
reg [5:0] minutes_out;
reg [3:0] hours_out;
reg am_pm_out;
reg [3:0] stopwatch_hours_out;
reg [5:0] stopwatch_minutes_out;
reg [5:0] stopwatch_seconds_out;
reg alarm_ring_out = 0;

// Execute the always blocks when the Clock or reset inputs are changing from 0 to 1 (positive edge of the signal)
always @ (posedge(Clk_1sec), posedge(reset_in), posedge(set_time_in)) begin
    
    if (reset_in) begin // Check for active high reset and reset the time.
        seconds_out = 0;
        minutes_out = 0;
        hours_out = 12;
        am_pm_out = 0; 
    end
    
    else if (set_time_in) begin // Set time manually
        seconds_out = 0;
        minutes_out = set_minute_in;
        hours_out = set_hour_in;
        am_pm_out = set_ampm_in; 
    end
    
    else if (Clk_1sec) begin // At the beginning of each second
        seconds_out = seconds_out + 1; // Increment sec
        if (seconds_out == 60) begin // Check for max value of sec
            seconds_out = 0; // Reset seconds
            minutes_out = minutes_out + 1; // Increment minutes
            if (minutes_out == 60) begin // Check for max value of min
                minutes_out = 0; // Reset minutes
                hours_out = hours_out + 1; // Increment hours
                if (hours_out == 12) begin // Check for max value of hours
                    am_pm_out = ~am_pm_out; // Toggle am_pm
                end
                else if (hours_out == 13) begin
                    hours_out = 1;
                end
            end
        end
        alarm_ring_out = !((hours_out^alarm_hour_in) | (minutes_out^alarm_minute_in) | (am_pm_out^alarm_ampm_in)); // Compare alarm time with present time
    end

end

always @ (posedge(Clk_1sec), posedge(stopwatch_reset_in)) begin

    if (stopwatch_reset_in) begin // Check for active high reset and reset the time.
        stopwatch_seconds_out = 0;
        stopwatch_minutes_out = 0;
        stopwatch_hours_out = 0; 
    end
            
    else if (stopwatch_on_in) begin // At the beginning of each second
        stopwatch_seconds_out = stopwatch_seconds_out + 1;
        // Increment sec
        if (stopwatch_seconds_out == 60) begin // Check for max value of sec
            stopwatch_seconds_out = 0; // Reset seconds
            stopwatch_minutes_out = stopwatch_minutes_out + 1;
            // Increment minutes
            if (stopwatch_minutes_out == 60) begin // Check for max value of min
                stopwatch_minutes_out = 0; // Reset minutes
                stopwatch_hours_out = stopwatch_hours_out + 1;
                // Increment hours
                if (stopwatch_hours_out == 24) begin // Check for max value of hours
                    stopwatch_hours_out = 0; // Reset hours
                end
            end
        end
    end
end

endmodule

tb_stopwatch.v
`timescale 1ns/1ps
`include "digital_clock.v"

module tb_stopwatch;

// Outputs
wire [5:0] seconds_out;
wire [5:0] minutes_out;
wire [3:0] hours_out;
wire am_pm_out;
wire [3:0] stopwatch_hours_out;
wire [5:0] stopwatch_minutes_out;
wire [5:0] stopwatch_seconds_out;
wire alarm_ring_out; 

// Inputs
reg Clk_1sec; // Clock with 1 Hz frequency
reg reset_in; // Active high reset
reg set_time_in; // Input 1 to select set time option
reg [3:0] set_hour_in; // Input hour
reg [5:0] set_minute_in; // Input minute
reg set_ampm_in; // 0 for am and 1 for pm
reg [3:0] alarm_hour_in;
reg [5:0] alarm_minute_in;
reg alarm_ampm_in; // 0 for am and 1 for pm
reg stopwatch_on_in;
reg stopwatch_reset_in;

digital_clock dc(
    seconds_out,
    minutes_out,
    hours_out,
    am_pm_out,
    stopwatch_hours_out,
    stopwatch_minutes_out,
    stopwatch_seconds_out,
    alarm_ring_out, 
    Clk_1sec, 
    reset_in, 
    set_time_in, 
    set_hour_in, 
    set_minute_in, 
    set_ampm_in,
    alarm_hour_in,
    alarm_minute_in,
    alarm_ampm_in, 
    stopwatch_on_in,
    stopwatch_reset_in
); 

initial begin
    #0 Clk_1sec = 1;
    forever #0.5 Clk_1sec = ~Clk_1sec;
end

initial begin
    $dumpfile("stopwatch.vcd");
    $dumpvars(0, tb_stopwatch);

    #0 
    stopwatch_reset_in = 1;
    stopwatch_on_in = 1;
    #0.1
    stopwatch_reset_in = 0;
    #19.9
    stopwatch_on_in = 0;
    #10 
    stopwatch_on_in = 1;
    #30 
    stopwatch_reset_in = 1;
    #0.1
    stopwatch_reset_in = 0;
    #139.9
    $finish;
end

endmodule

stopwatch.vcd
$date
	Mon Dec 04 20:06:10 2023
$end
$version
	Icarus Verilog
$end
$timescale
	1ps
$end
$scope module tb_stopwatch $end
$var wire 6 ! stopwatch_seconds_out [5:0] $end
$var wire 6 " stopwatch_minutes_out [5:0] $end
$var wire 4 # stopwatch_hours_out [3:0] $end
$var wire 6 $ seconds_out [5:0] $end
$var wire 6 % minutes_out [5:0] $end
$var wire 4 & hours_out [3:0] $end
$var wire 1 ' am_pm_out $end
$var wire 1 ( alarm_ring_out $end
$var reg 1 ) Clk_1sec $end
$var reg 1 * alarm_ampm_in $end
$var reg 4 + alarm_hour_in [3:0] $end
$var reg 6 , alarm_minute_in [5:0] $end
$var reg 1 - reset_in $end
$var reg 1 . set_ampm_in $end
$var reg 4 / set_hour_in [3:0] $end
$var reg 6 0 set_minute_in [5:0] $end
$var reg 1 1 set_time_in $end
$var reg 1 2 stopwatch_on_in $end
$var reg 1 3 stopwatch_reset_in $end
$scope module dc $end
$var wire 1 ) Clk_1sec $end
$var wire 1 * alarm_ampm_in $end
$var wire 4 4 alarm_hour_in [3:0] $end
$var wire 6 5 alarm_minute_in [5:0] $end
$var wire 1 - reset_in $end
$var wire 1 . set_ampm_in $end
$var wire 4 6 set_hour_in [3:0] $end
$var wire 6 7 set_minute_in [5:0] $end
$var wire 1 1 set_time_in $end
$var wire 1 2 stopwatch_on_in $end
$var wire 1 3 stopwatch_reset_in $end
$var reg 1 ( alarm_ring_out $end
$var reg 1 ' am_pm_out $end
$var reg 4 8 hours_out [3:0] $end
$var reg 6 9 minutes_out [5:0] $end
$var reg 6 : seconds_out [5:0] $end
$var reg 4 ; stopwatch_hours_out [3:0] $end
$var reg 6 < stopwatch_minutes_out [5:0] $end
$var reg 6 = stopwatch_seconds_out [5:0] $end
$upscope $end
$upscope $end
$enddefinitions $end
$comment Show the parameter values. $end
$dumpall
$end
#0
$dumpvars
b0 =
b0 <
b0 ;
bx :
bx 9
bx 8
bx 7
bx 6
bx 5
bx 4
13
12
x1
bx 0
bx /
x.
x-
bx ,
bx +
x*
1)
x(
x'
bx &
bx %
bx $
b0 #
b0 "
b0 !
$end
#100
03
#500
0)
#1000
b1 !
b1 =
1)
#1500
0)
#2000
b10 !
b10 =
1)
#2500
0)
#3000
b11 !
b11 =
1)
#3500
0)
#4000
b100 !
b100 =
1)
#4500
0)
#5000
b101 !
b101 =
1)
#5500
0)
#6000
b110 !
b110 =
1)
#6500
0)
#7000
b111 !
b111 =
1)
#7500
0)
#8000
b1000 !
b1000 =
1)
#8500
0)
#9000
b1001 !
b1001 =
1)
#9500
0)
#10000
b1010 !
b1010 =
1)
#10500
0)
#11000
b1011 !
b1011 =
1)
#11500
0)
#12000
b1100 !
b1100 =
1)
#12500
0)
#13000
b1101 !
b1101 =
1)
#13500
0)
#14000
b1110 !
b1110 =
1)
#14500
0)
#15000
b1111 !
b1111 =
1)
#15500
0)
#16000
b10000 !
b10000 =
1)
#16500
0)
#17000
b10001 !
b10001 =
1)
#17500
0)
#18000
b10010 !
b10010 =
1)
#18500
0)
#19000
b10011 !
b10011 =
1)
#19500
0)
#20000
1)
02
#20500
0)
#21000
1)
#21500
0)
#22000
1)
#22500
0)
#23000
1)
#23500
0)
#24000
1)
#24500
0)
#25000
1)
#25500
0)
#26000
1)
#26500
0)
#27000
1)
#27500
0)
#28000
1)
#28500
0)
#29000
1)
#29500
0)
#30000
b10100 !
b10100 =
1)
12
#30500
0)
#31000
b10101 !
b10101 =
1)
#31500
0)
#32000
b10110 !
b10110 =
1)
#32500
0)
#33000
b10111 !
b10111 =
1)
#33500
0)
#34000
b11000 !
b11000 =
1)
#34500
0)
#35000
b11001 !
b11001 =
1)
#35500
0)
#36000
b11010 !
b11010 =
1)
#36500
0)
#37000
b11011 !
b11011 =
1)
#37500
0)
#38000
b11100 !
b11100 =
1)
#38500
0)
#39000
b11101 !
b11101 =
1)
#39500
0)
#40000
b11110 !
b11110 =
1)
#40500
0)
#41000
b11111 !
b11111 =
1)
#41500
0)
#42000
b100000 !
b100000 =
1)
#42500
0)
#43000
b100001 !
b100001 =
1)
#43500
0)
#44000
b100010 !
b100010 =
1)
#44500
0)
#45000
b100011 !
b100011 =
1)
#45500
0)
#46000
b100100 !
b100100 =
1)
#46500
0)
#47000
b100101 !
b100101 =
1)
#47500
0)
#48000
b100110 !
b100110 =
1)
#48500
0)
#49000
b100111 !
b100111 =
1)
#49500
0)
#50000
b101000 !
b101000 =
1)
#50500
0)
#51000
b101001 !
b101001 =
1)
#51500
0)
#52000
b101010 !
b101010 =
1)
#52500
0)
#53000
b101011 !
b101011 =
1)
#53500
0)
#54000
b101100 !
b101100 =
1)
#54500
0)
#55000
b101101 !
b101101 =
1)
#55500
0)
#56000
b101110 !
b101110 =
1)
#56500
0)
#57000
b101111 !
b101111 =
1)
#57500
0)
#58000
b110000 !
b110000 =
1)
#58500
0)
#59000
b110001 !
b110001 =
1)
#59500
0)
#60000
b0 !
b0 =
1)
13
#60100
03
#60500
0)
#61000
b1 !
b1 =
1)
#61500
0)
#62000
b10 !
b10 =
1)
#62500
0)
#63000
b11 !
b11 =
1)
#63500
0)
#64000
b100 !
b100 =
1)
#64500
0)
#65000
b101 !
b101 =
1)
#65500
0)
#66000
b110 !
b110 =
1)
#66500
0)
#67000
b111 !
b111 =
1)
#67500
0)
#68000
b1000 !
b1000 =
1)
#68500
0)
#69000
b1001 !
b1001 =
1)
#69500
0)
#70000
b1010 !
b1010 =
1)
#70500
0)
#71000
b1011 !
b1011 =
1)
#71500
0)
#72000
b1100 !
b1100 =
1)
#72500
0)
#73000
b1101 !
b1101 =
1)
#73500
0)
#74000
b1110 !
b1110 =
1)
#74500
0)
#75000
b1111 !
b1111 =
1)
#75500
0)
#76000
b10000 !
b10000 =
1)
#76500
0)
#77000
b10001 !
b10001 =
1)
#77500
0)
#78000
b10010 !
b10010 =
1)
#78500
0)
#79000
b10011 !
b10011 =
1)
#79500
0)
#80000
b10100 !
b10100 =
1)
#80500
0)
#81000
b10101 !
b10101 =
1)
#81500
0)
#82000
b10110 !
b10110 =
1)
#82500
0)
#83000
b10111 !
b10111 =
1)
#83500
0)
#84000
b11000 !
b11000 =
1)
#84500
0)
#85000
b11001 !
b11001 =
1)
#85500
0)
#86000
b11010 !
b11010 =
1)
#86500
0)
#87000
b11011 !
b11011 =
1)
#87500
0)
#88000
b11100 !
b11100 =
1)
#88500
0)
#89000
b11101 !
b11101 =
1)
#89500
0)
#90000
b11110 !
b11110 =
1)
#90500
0)
#91000
b11111 !
b11111 =
1)
#91500
0)
#92000
b100000 !
b100000 =
1)
#92500
0)
#93000
b100001 !
b100001 =
1)
#93500
0)
#94000
b100010 !
b100010 =
1)
#94500
0)
#95000
b100011 !
b100011 =
1)
#95500
0)
#96000
b100100 !
b100100 =
1)
#96500
0)
#97000
b100101 !
b100101 =
1)
#97500
0)
#98000
b100110 !
b100110 =
1)
#98500
0)
#99000
b100111 !
b100111 =
1)
#99500
0)
#100000
b101000 !
b101000 =
1)
#100500
0)
#101000
b101001 !
b101001 =
1)
#101500
0)
#102000
b101010 !
b101010 =
1)
#102500
0)
#103000
b101011 !
b101011 =
1)
#103500
0)
#104000
b101100 !
b101100 =
1)
#104500
0)
#105000
b101101 !
b101101 =
1)
#105500
0)
#106000
b101110 !
b101110 =
1)
#106500
0)
#107000
b101111 !
b101111 =
1)
#107500
0)
#108000
b110000 !
b110000 =
1)
#108500
0)
#109000
b110001 !
b110001 =
1)
#109500
0)
#110000
b110010 !
b110010 =
1)
#110500
0)
#111000
b110011 !
b110011 =
1)
#111500
0)
#112000
b110100 !
b110100 =
1)
#112500
0)
#113000
b110101 !
b110101 =
1)
#113500
0)
#114000
b110110 !
b110110 =
1)
#114500
0)
#115000
b110111 !
b110111 =
1)
#115500
0)
#116000
b111000 !
b111000 =
1)
#116500
0)
#117000
b111001 !
b111001 =
1)
#117500
0)
#118000
b111010 !
b111010 =
1)
#118500
0)
#119000
b111011 !
b111011 =
1)
#119500
0)
#120000
b1 "
b1 <
b0 !
b0 =
1)
#120500
0)
#121000
b1 !
b1 =
1)
#121500
0)
#122000
b10 !
b10 =
1)
#122500
0)
#123000
b11 !
b11 =
1)
#123500
0)
#124000
b100 !
b100 =
1)
#124500
0)
#125000
b101 !
b101 =
1)
#125500
0)
#126000
b110 !
b110 =
1)
#126500
0)
#127000
b111 !
b111 =
1)
#127500
0)
#128000
b1000 !
b1000 =
1)
#128500
0)
#129000
b1001 !
b1001 =
1)
#129500
0)
#130000
b1010 !
b1010 =
1)
#130500
0)
#131000
b1011 !
b1011 =
1)
#131500
0)
#132000
b1100 !
b1100 =
1)
#132500
0)
#133000
b1101 !
b1101 =
1)
#133500
0)
#134000
b1110 !
b1110 =
1)
#134500
0)
#135000
b1111 !
b1111 =
1)
#135500
0)
#136000
b10000 !
b10000 =
1)
#136500
0)
#137000
b10001 !
b10001 =
1)
#137500
0)
#138000
b10010 !
b10010 =
1)
#138500
0)
#139000
b10011 !
b10011 =
1)
#139500
0)
#140000
b10100 !
b10100 =
1)
#140500
0)
#141000
b10101 !
b10101 =
1)
#141500
0)
#142000
b10110 !
b10110 =
1)
#142500
0)
#143000
b10111 !
b10111 =
1)
#143500
0)
#144000
b11000 !
b11000 =
1)
#144500
0)
#145000
b11001 !
b11001 =
1)
#145500
0)
#146000
b11010 !
b11010 =
1)
#146500
0)
#147000
b11011 !
b11011 =
1)
#147500
0)
#148000
b11100 !
b11100 =
1)
#148500
0)
#149000
b11101 !
b11101 =
1)
#149500
0)
#150000
b11110 !
b11110 =
1)
#150500
0)
#151000
b11111 !
b11111 =
1)
#151500
0)
#152000
b100000 !
b100000 =
1)
#152500
0)
#153000
b100001 !
b100001 =
1)
#153500
0)
#154000
b100010 !
b100010 =
1)
#154500
0)
#155000
b100011 !
b100011 =
1)
#155500
0)
#156000
b100100 !
b100100 =
1)
#156500
0)
#157000
b100101 !
b100101 =
1)
#157500
0)
#158000
b100110 !
b100110 =
1)
#158500
0)
#159000
b100111 !
b100111 =
1)
#159500
0)
#160000
b101000 !
b101000 =
1)
#160500
0)
#161000
b101001 !
b101001 =
1)
#161500
0)
#162000
b101010 !
b101010 =
1)
#162500
0)
#163000
b101011 !
b101011 =
1)
#163500
0)
#164000
b101100 !
b101100 =
1)
#164500
0)
#165000
b101101 !
b101101 =
1)
#165500
0)
#166000
b101110 !
b101110 =
1)
#166500
0)
#167000
b101111 !
b101111 =
1)
#167500
0)
#168000
b110000 !
b110000 =
1)
#168500
0)
#169000
b110001 !
b110001 =
1)
#169500
0)
#170000
b110010 !
b110010 =
1)
#170500
0)
#171000
b110011 !
b110011 =
1)
#171500
0)
#172000
b110100 !
b110100 =
1)
#172500
0)
#173000
b110101 !
b110101 =
1)
#173500
0)
#174000
b110110 !
b110110 =
1)
#174500
0)
#175000
b110111 !
b110111 =
1)
#175500
0)
#176000
b111000 !
b111000 =
1)
#176500
0)
#177000
b111001 !
b111001 =
1)
#177500
0)
#178000
b111010 !
b111010 =
1)
#178500
0)
#179000
b111011 !
b111011 =
1)
#179500
0)
#180000
b10 "
b10 <
b0 !
b0 =
1)
#180500
0)
#181000
b1 !
b1 =
1)
#181500
0)
#182000
b10 !
b10 =
1)
#182500
0)
#183000
b11 !
b11 =
1)
#183500
0)
#184000
b100 !
b100 =
1)
#184500
0)
#185000
b101 !
b101 =
1)
#185500
0)
#186000
b110 !
b110 =
1)
#186500
0)
#187000
b111 !
b111 =
1)
#187500
0)
#188000
b1000 !
b1000 =
1)
#188500
0)
#189000
b1001 !
b1001 =
1)
#189500
0)
#190000
b1010 !
b1010 =
1)
#190500
0)
#191000
b1011 !
b1011 =
1)
#191500
0)
#192000
b1100 !
b1100 =
1)
#192500
0)
#193000
b1101 !
b1101 =
1)
#193500
0)
#194000
b1110 !
b1110 =
1)
#194500
0)
#195000
b1111 !
b1111 =
1)
#195500
0)
#196000
b10000 !
b10000 =
1)
#196500
0)
#197000
b10001 !
b10001 =
1)
#197500
0)
#198000
b10010 !
b10010 =
1)
#198500
0)
#199000
b10011 !
b10011 =
1)
#199500
0)
#200000
b10100 !
b10100 =
1)
